ews_builder/__init__.py
ews_builder/__main__.py
ews_builder/builder.py
ews_builder/core.py
ews_builder/headers.py
ews_builder/messages.py
ews_builder/services.py
ews_builder/types.py
ews_builder/utils/__init__.py
ews_builder/utils/logger.py
ews_builder/utils/version.py
ews_builder-0.0.1.dist-info/LICENSE.md
ews_builder-0.0.1.dist-info/METADATA
ews_builder-0.0.1.dist-info/WHEEL
ews_builder-0.0.1.dist-info/entry_points.txt
ews_builder-0.0.1.dist-info/top_level.txt
ews_builder-0.0.1.dist-info/RECORD
