Metadata-Version: 2.1
Name: ews-builder
Version: 0.0.1
Summary: A Python package created using carcass
Home-page: https://github.com/swimlane/ews-builder
Author: MSAdministrator
Author-email: rickardja@live.com
License: MIT
Keywords: carcass
Platform: UNKNOWN
Requires-Python: >=2.6, !=3.0.*, !=3.1.*, !=3.2.*, <4
Requires-Dist: pyyaml
Requires-Dist: fire
Requires-Dist: pick
